directrix_pkg/__init__.py
directrix_pkg-0.0.2.dist-info/DESCRIPTION.rst
directrix_pkg-0.0.2.dist-info/METADATA
directrix_pkg-0.0.2.dist-info/RECORD
directrix_pkg-0.0.2.dist-info/WHEEL
directrix_pkg-0.0.2.dist-info/metadata.json
directrix_pkg-0.0.2.dist-info/top_level.txt
