Metadata-Version: 2.0
Name: directrix-pkg
Version: 0.0.2
Summary: A small example package
Home-page: https://github.com/directrix1/directrix_pkg
Author: Edward Flick
Author-email: directrix1@gmail.com
License: UNKNOWN
Platform: UNKNOWN
Classifier: Programming Language :: Python :: 3
Classifier: License :: OSI Approved :: MIT License
Classifier: Operating System :: OS Independent
